{
  "name": "Tempus Totus",
  "author": "Protesilaos Stavrou (https://protesilaos.com)",
  "variant": "light",
  "color_01": "#4a484d",
  "color_02": "#a50000",
  "color_03": "#005d26",
  "color_04": "#714700",
  "color_05": "#1d3ccf",
  "color_06": "#88267a",
  "color_07": "#185570",
  "color_08": "#efefef",
  "color_09": "#5e4b4f",
  "color_10": "#992030",
  "color_11": "#4a5500",
  "color_12": "#8a3600",
  "color_13": "#2d45b0",
  "color_14": "#700dc9",
  "color_15": "#005289",
  "color_16": "#ffffff",
  "background": "#ffffff",
  "foreground": "#4a484d",
  "cursor": "#4a484d",
  "hash": "528eb84e064185448c049b5eaa1fb8c29b9faae47c736479cd1dde9ae955003c"
}