{
  "name": "Wombat",
  "author": "",
  "variant": "",
  "color_01": "#000000",
  "color_02": "#FF615A",
  "color_03": "#B1E969",
  "color_04": "#EBD99C",
  "color_05": "#5DA9F6",
  "color_06": "#E86AFF",
  "color_07": "#82FFF7",
  "color_08": "#DEDACF",
  "color_09": "#313131",
  "color_10": "#F58C80",
  "color_11": "#DDF88F",
  "color_12": "#EEE5B2",
  "color_13": "#A5C7FF",
  "color_14": "#DDAAFF",
  "color_15": "#B7FFF9",
  "color_16": "#FFFFFF",
  "background": "#171717",
  "foreground": "#DEDACF",
  "cursor": "#DEDACF",
  "hash": "c5f0a5b17dfd556ce8ebb47996b3c9eb424ceb36f829434d1066b7d8970df213"
}