{"color_01": "#4D4D4D", "color_02": "#705050", "color_03": "#60B48A", "color_04": "#F0DFAF", "color_05": "#506070", "color_06": "#DC8CC3", "color_07": "#8CD0D3", "color_08": "#DCDCCC", "color_09": "#709080", "color_10": "#DCA3A3", "color_11": "#C3BF9F", "color_12": "#E0CF9F", "color_13": "#94BFF3", "color_14": "#EC93D3", "color_15": "#93E0E3", "color_16": "#FFFFFF", "name": "Zenburn", "foreground": "#DCDCCC", "background": "#3F3F3F", "cursor": "#DCDCCC", "hash": "f7fcd9bd19ab1bb68da10e3917067d776da39520826940492a0e51f3328ccfc3"}